alpha_connector/__init__.py
alpha_connector/__main__.py
alpha_connector/alpha_connector.py
alpha_connector/alpha_xarray.py
alpha_connector/config.yaml
alpha_connector/example.py
alpha_connector-0.1.1.dist-info/LICENSE
alpha_connector-0.1.1.dist-info/METADATA
alpha_connector-0.1.1.dist-info/WHEEL
alpha_connector-0.1.1.dist-info/entry_points.txt
alpha_connector-0.1.1.dist-info/RECORD
