Metadata-Version: 2.1
Name: alpha_connector
Version: 0.1.1
Summary: Awesome `alpha_connector` is a Python cli/package created with https://github.com/TezRomacH/python-package-template
Home-page: https://github.com/AlphaConnector/alpha_connector
License: MIT
Author: Clovin4
Author-email: christian70401@gmail.com
Requires-Python: >=3.11,<4.0
Classifier: Development Status :: 3 - Alpha
Classifier: Intended Audience :: Developers
Classifier: License :: OSI Approved :: MIT License
Classifier: Operating System :: OS Independent
Classifier: Programming Language :: Python :: 3
Classifier: Programming Language :: Python :: 3.11
Classifier: Programming Language :: Python :: 3.12
Classifier: Programming Language :: Python :: 3.9
Classifier: Topic :: Software Development :: Libraries :: Python Modules
Requires-Dist: numpy (>=1.26.4,<2.0.0)
Requires-Dist: pandas (>=2.2.1,<3.0.0)
Requires-Dist: python-dotenv (>=1.0.1,<2.0.0)
Requires-Dist: rich (>=13.7.1,<14.0.0)
Requires-Dist: typer[all] (>=0.9.0,<0.10.0)
Requires-Dist: xarray (>=2024.2.0,<2025.0.0)
Project-URL: Repository, https://github.com/AlphaConnector/alpha_connector
